deformable_attention/__init__.py
deformable_attention/deformable_attention_1d.py
deformable_attention/deformable_attention_2d.py
deformable_attention/deformable_attention_3d.py
deformable_attention-0.0.20.dist-info/LICENSE
deformable_attention-0.0.20.dist-info/METADATA
deformable_attention-0.0.20.dist-info/WHEEL
deformable_attention-0.0.20.dist-info/top_level.txt
deformable_attention-0.0.20.dist-info/RECORD
